<?xml version="1.0" encoding="UTF-8"?>
<!DOCTYPE mapper PUBLIC "-//mybatis.org//DTD Mapper 3.0//EN" "http://mybatis.org/dtd/mybatis-3-mapper.dtd">
<mapper namespace="com.newx.dao.UserQuestionsMapper">
  <resultMap id="BaseResultMap" type="com.newx.pojo.UserQuestions">
    <!--
      WARNING - @mbggenerated
      This element is automatically generated by MyBatis Generator, do not modify.
    -->
    <constructor>
      <idArg column="user_id" javaType="java.lang.Integer" jdbcType="INTEGER" />
      <idArg column="question_id" javaType="java.lang.Integer" jdbcType="INTEGER" />
      <arg column="note" javaType="java.lang.String" jdbcType="VARCHAR" />
    </constructor>
  </resultMap>
  <sql id="Base_Column_List">
    <!--
      WARNING - @mbggenerated
      This element is automatically generated by MyBatis Generator, do not modify.
    -->
    user_id, question_id, note
  </sql>
  <select id="selectByPrimaryKey" parameterType="com.newx.pojo.UserQuestionsKey" resultMap="BaseResultMap">
    <!--
      WARNING - @mbggenerated
      This element is automatically generated by MyBatis Generator, do not modify.
    -->
    select 
    <include refid="Base_Column_List" />
    from user_questions
    where user_id = #{userId,jdbcType=INTEGER}
      and question_id = #{questionId,jdbcType=INTEGER}
  </select>
  <delete id="deleteByPrimaryKey" parameterType="com.newx.pojo.UserQuestionsKey">
    <!--
      WARNING - @mbggenerated
      This element is automatically generated by MyBatis Generator, do not modify.
    -->
    delete from user_questions
    where user_id = #{userId,jdbcType=INTEGER}
      and question_id = #{questionId,jdbcType=INTEGER}
  </delete>
  <insert id="insert" parameterType="com.newx.pojo.UserQuestions">
    <!--
      WARNING - @mbggenerated
      This element is automatically generated by MyBatis Generator, do not modify.
    -->
    insert into user_questions (user_id, question_id, note
      )
    values (#{userId,jdbcType=INTEGER}, #{questionId,jdbcType=INTEGER}, #{note,jdbcType=VARCHAR}
      )
  </insert>
  <insert id="insertSelective" parameterType="com.newx.pojo.UserQuestions">
    <!--
      WARNING - @mbggenerated
      This element is automatically generated by MyBatis Generator, do not modify.
    -->
    insert into user_questions
    <trim prefix="(" suffix=")" suffixOverrides=",">
      <if test="userId != null">
        user_id,
      </if>
      <if test="questionId != null">
        question_id,
      </if>
      <if test="note != null">
        note,
      </if>
    </trim>
    <trim prefix="values (" suffix=")" suffixOverrides=",">
      <if test="userId != null">
        #{userId,jdbcType=INTEGER},
      </if>
      <if test="questionId != null">
        #{questionId,jdbcType=INTEGER},
      </if>
      <if test="note != null">
        #{note,jdbcType=VARCHAR},
      </if>
    </trim>
  </insert>
  <update id="updateByPrimaryKeySelective" parameterType="com.newx.pojo.UserQuestions">
    <!--
      WARNING - @mbggenerated
      This element is automatically generated by MyBatis Generator, do not modify.
    -->
    update user_questions
    <set>
      <if test="note != null">
        note = #{note,jdbcType=VARCHAR},
      </if>
    </set>
    where user_id = #{userId,jdbcType=INTEGER}
      and question_id = #{questionId,jdbcType=INTEGER}
  </update>
  <update id="updateByPrimaryKey" parameterType="com.newx.pojo.UserQuestions">
    <!--
      WARNING - @mbggenerated
      This element is automatically generated by MyBatis Generator, do not modify.
    -->
    update user_questions
    set note = #{note,jdbcType=VARCHAR}
    where user_id = #{userId,jdbcType=INTEGER}
      and question_id = #{questionId,jdbcType=INTEGER}
  </update>
</mapper>